test_project/__init__.py
test_project/urls.py
webmaster_verification/__init__.py
webmaster_verification/models.py
webmaster_verification/tests.py
webmaster_verification/urls.py
webmaster_verification/views.py
webmaster_verification/templates/webmaster_verification/alexa_verify_template.html
webmaster_verification/templates/webmaster_verification/bing_verify_template.xml
webmaster_verification/templates/webmaster_verification/google_verify_template.html
webmaster_verification/templates/webmaster_verification/majestic_verify_template.txt
webmaster_verification/templates/webmaster_verification/yandex_verify_template.html
django_webmaster_verification-0.4.3.dist-info/LICENSE
django_webmaster_verification-0.4.3.dist-info/METADATA
django_webmaster_verification-0.4.3.dist-info/WHEEL
django_webmaster_verification-0.4.3.dist-info/top_level.txt
django_webmaster_verification-0.4.3.dist-info/zip-safe
django_webmaster_verification-0.4.3.dist-info/RECORD
