Metadata-Version: 2.1
Name: django-webmaster-verification
Version: 0.4.3
Summary: Webmaster tools verification for Django
Home-page: http://github.com/nkuttler/django-webmaster-verification
Author: Nicolas Kuttler
Author-email: pypi@kuttler.eu
License: BSD
Platform: UNKNOWN
Classifier: Development Status :: 5 - Production/Stable
Classifier: Environment :: Web Environment
Classifier: Intended Audience :: Developers
Classifier: License :: OSI Approved :: BSD License
Classifier: Operating System :: OS Independent
Classifier: Programming Language :: Python
Classifier: Framework :: Django
Classifier: Programming Language :: Python :: 3.5
Classifier: Programming Language :: Python :: 3.6
Classifier: Programming Language :: Python :: 3.7
Classifier: Programming Language :: Python :: 3.8
Requires-Dist: Django (>=3.0)
